face_analysis/__init__.py
face_analysis/version.py
face_analysis/commons/__init__.py
face_analysis/commons/folder_utils.py
face_analysis/commons/get_weights.py
face_analysis/commons/logger.py
face_analysis/emotions/__init__.py
face_analysis/emotions/pipeline.py
face_analysis/emotions/results.py
face_analysis/emotions/utils.py
face_analysis/emotions/vis.py
face_analysis/emotions/data/emotion_model.hdf5
face_analysis/emotions/data/haarcascade_frontalface_default.xml
face_analysis/emotions/data/mmod_human_face_detector.dat
face_analysis/eyes/__init__.py
face_analysis/eyes/model.py
face_analysis/eyes/pipeline.py
face_analysis/eyes/results.py
face_analysis/eyes/utils.py
face_analysis/eyes/vis.py
face_analysis/face_detection/LICENSE
face_analysis/face_detection/MANIFEST.in
face_analysis/face_detection/README.md
face_analysis/face_detection/build.cmd
face_analysis/face_detection/publish.cmd
face_analysis/face_detection/requirements.txt
face_analysis/face_detection/setup.py
face_analysis/face_detection/test.py
face_analysis/face_detection/examples/batman.jpg
face_analysis/face_detection/examples/obama.jpg
face_analysis/face_detection/examples/trump.jpg
face_analysis/face_detection/face_detection/__init__.py
face_analysis/face_detection/face_detection/_version.py
face_analysis/face_detection/face_detection/alignment.py
face_analysis/face_detection/face_detection/detector.py
face_analysis/face_detection/face_detection/weights/mobilenet0.25_Final.pth
face_analysis/face_detection/images/gpu_batch.png
face_analysis/gazes/__init__.py
face_analysis/gazes/model.py
face_analysis/gazes/pipeline.py
face_analysis/gazes/results.py
face_analysis/gazes/utils.py
face_analysis/gazes/vis.py
face_analysis_kit-1.0.0.dist-info/licenses/LICENSE.txt
face_analysis_kit-1.0.0.dist-info/METADATA
face_analysis_kit-1.0.0.dist-info/WHEEL
face_analysis_kit-1.0.0.dist-info/top_level.txt
face_analysis_kit-1.0.0.dist-info/RECORD
