Metadata-Version: 2.4
Name: face-analysis-kit
Version: 1.0.0
Summary: A package for analyzing faces in images to detect eye state, gaze direction, and facial expressions
Author: Ahmed Salim
License: MIT License
Project-URL: homepath, https://github.com/ahmedsalim3/face-analysis.git
Project-URL: repository, https://github.com/ahmedsalim3/face-analysis.git
Keywords: facial-expressions,gaze-estimation,eye-tracking,deep-learning,pytorch,tensorflow
Requires-Python: >=3.10
License-File: LICENSE.txt
Requires-Dist: dlib>=19.24.6
Requires-Dist: facenet-pytorch==2.6.0
Requires-Dist: gdown>=5.2.0
Requires-Dist: matplotlib>=3.3.4
Requires-Dist: numpy>=1.19.5
Requires-Dist: opencv-python>=4.5.5
Requires-Dist: pandas>=1.1.5
Requires-Dist: pillow>=8.4.0
Requires-Dist: scipy>=1.5.4
Requires-Dist: tensorflow>=2.10
Requires-Dist: torch>=1.10.1
Requires-Dist: torchvision>=0.11.2
Provides-Extra: dev
Requires-Dist: ipython; extra == "dev"
Requires-Dist: mypy; extra == "dev"
Requires-Dist: pre-commit; extra == "dev"
Requires-Dist: pytest; extra == "dev"
Requires-Dist: pytest-coverage; extra == "dev"
Requires-Dist: ruff; extra == "dev"
Dynamic: license-file
